muse_maskgit_pytorch/__init__.py
muse_maskgit_pytorch/attend.py
muse_maskgit_pytorch/muse_maskgit_pytorch.py
muse_maskgit_pytorch/t5.py
muse_maskgit_pytorch/trainers.py
muse_maskgit_pytorch/vqgan_vae.py
muse_maskgit_pytorch-0.3.5.dist-info/LICENSE
muse_maskgit_pytorch-0.3.5.dist-info/METADATA
muse_maskgit_pytorch-0.3.5.dist-info/WHEEL
muse_maskgit_pytorch-0.3.5.dist-info/top_level.txt
muse_maskgit_pytorch-0.3.5.dist-info/RECORD
