Metadata-Version: 2.1
Name: muse-maskgit-pytorch
Version: 0.3.5
Summary: MUSE - Text-to-Image Generation via Masked Generative Transformers, in Pytorch
Home-page: https://github.com/lucidrains/muse-maskgit-pytorch
Author: Phil Wang
Author-email: lucidrains@gmail.com
License: MIT
Keywords: artificial intelligence,deep learning,transformers,attention mechanism,text-to-image
Classifier: Development Status :: 4 - Beta
Classifier: Intended Audience :: Developers
Classifier: Topic :: Scientific/Engineering :: Artificial Intelligence
Classifier: License :: OSI Approved :: MIT License
Classifier: Programming Language :: Python :: 3.6
License-File: LICENSE
Requires-Dist: accelerate
Requires-Dist: beartype
Requires-Dist: einops >=0.7
Requires-Dist: ema-pytorch >=0.2.2
Requires-Dist: memory-efficient-attention-pytorch >=0.1.4
Requires-Dist: pillow
Requires-Dist: sentencepiece
Requires-Dist: torch >=1.6
Requires-Dist: transformers
Requires-Dist: torchvision
Requires-Dist: tqdm
Requires-Dist: vector-quantize-pytorch >=1.11.8
